colorcodeconvert/__init__.py
colorcodeconvert/colorcodes.py
colorcodeconvert/convert.py
colorcodeconvert/errors.py
colorcodeconvert/types.py
colorcodeconvert-1.1.2.dist-info/LICENSE
colorcodeconvert-1.1.2.dist-info/METADATA
colorcodeconvert-1.1.2.dist-info/WHEEL
colorcodeconvert-1.1.2.dist-info/top_level.txt
colorcodeconvert-1.1.2.dist-info/RECORD
