Metadata-Version: 2.1
Name: colorcodeconvert
Version: 1.1.2
Summary: A simple library to convert color codes.
Home-page: https://github.com/Simoso68/colorcodeconvert
Author: Simoso68
Maintainer: Simoso68
License: GNU General Public License version 3
Project-URL: Source, https://github.com/Simoso68/colorcodeconvert
Project-URL: Issues, https://github.com/Simoso68/colorcodeconvert/issues
Project-URL: Documentation, https://github.com/Simoso68/colorcodeconvert/wiki
Keywords: color,hex,rgb
Classifier: License :: OSI Approved :: GNU General Public License v3 (GPLv3)
Classifier: Intended Audience :: Developers
Classifier: Intended Audience :: End Users/Desktop
Classifier: Intended Audience :: Information Technology
Classifier: Programming Language :: Python :: 3
Classifier: Programming Language :: Python :: 3.6
Classifier: Programming Language :: Python :: 3.7
Classifier: Programming Language :: Python :: 3.8
Classifier: Programming Language :: Python :: 3.9
Classifier: Programming Language :: Python :: 3.10
Classifier: Programming Language :: Python :: 3.11
Classifier: Operating System :: OS Independent
Classifier: Natural Language :: English
Requires-Python: >=3.6
License-File: LICENSE
